dfhealth/__init__.py
dfhealth/core.py
dfhealth/checks/base.py
dfhealth/checks/date_like.py
dfhealth/checks/duplicates.py
dfhealth/checks/id_like.py
dfhealth/checks/negative.py
dfhealth/checks/outlier.py
dfhealth-0.1.2.dist-info/licenses/LICENSE
dfhealth-0.1.2.dist-info/METADATA
dfhealth-0.1.2.dist-info/WHEEL
dfhealth-0.1.2.dist-info/top_level.txt
dfhealth-0.1.2.dist-info/RECORD
