Metadata-Version: 2.4
Name: dfhealth
Version: 0.1.2
Summary: Opinionated data health checks for pandas DataFrames
Author-email: Hamna Qaseem <contact.neuralgenix@gmail.com>
License: MIT
Classifier: Programming Language :: Python :: 3
Classifier: License :: OSI Approved :: MIT License
Classifier: Operating System :: OS Independent
Classifier: Topic :: Scientific/Engineering :: Information Analysis
License-File: LICENSE
Requires-Dist: pandas>=2.0.0
Dynamic: license-file
